{
  "$schema": "./node_modules/@openapitools/openapi-generator-cli/config.schema.json",
  "spaces": 2,
  "generator-cli": {
    "version": "7.3.0",
    "generators": {
      "datakatalog-java": {
        "inputSpec": "https://nvdbapiles.atlas.vegvesen.no/api-docs/datakatalog",
        "output": "datakatalog-java",
        "generatorName": "java",
        "library": "webclient",
        "apiPackage": "no.vegvesen.nvdb.datakatalog.api",
        "modelPackage": "no.vegvesen.nvdb.datakatalog.model",
        "globalProperty": "models,apis,modelDocs=false,modelTests=false,apiTests=false"
      },
      "datakatalog-kotlin": {
        "inputSpec": "https://nvdbapiles.atlas.vegvesen.no/api-docs/datakatalog",
        "output": "datakatalog-kotlin",
        "generatorName": "kotlin",
        "library": "multiplatform",
        "apiPackage": "no.vegvesen.nvdb.datakatalog.api",
        "modelPackage": "no.vegvesen.nvdb.datakatalog.model",
        "globalProperty": "models,apis,modelDocs=false,modelTests=false,apiTests=false",
        "additionalProperties": {
          "dateLibrary": "kotlinx-datetime",
          "sourceFolder": "src/main/kotlin"
        }
      },
      "datakatalog-ts": {
        "inputSpec": "https://nvdbapiles.atlas.vegvesen.no/api-docs/datakatalog",
        "output": "datakatalog-ts",
        "generatorName": "typescript-fetch"
      }
    }
  }
}